transformer_serving/__init__.py
transformer_serving/client/__init__.py
transformer_serving/client/_py2_var.py
transformer_serving/client/_py3_var.py
transformer_as_client-1.10.0.dist-info/METADATA
transformer_as_client-1.10.0.dist-info/WHEEL
transformer_as_client-1.10.0.dist-info/top_level.txt
transformer_as_client-1.10.0.dist-info/RECORD
