Metadata-Version: 2.1
Name: transformer-as-client
Version: 1.10.0
Summary: Use your pretrained models as service (client)
Home-page: UNKNOWN
Author: faith
Author-email: xianzixiang@gmail.com
License: MIT
Keywords: transformer pretrained model as service
Platform: UNKNOWN
Classifier: Programming Language :: Python :: 2.7
Classifier: Programming Language :: Python :: 3.6
Classifier: License :: OSI Approved :: MIT License
Classifier: Operating System :: OS Independent
Classifier: Topic :: Scientific/Engineering :: Artificial Intelligence
Requires-Dist: numpy
Requires-Dist: pyzmq (>=17.1.0)
